{
    "appKeys": {},
    "capabilities": [
        ""
    ],
    "companyName": "NetTek Ltd",
    "enableMultiJS": true,
    "longName": "UmpClicker",
    "projectType": "native",
    "resources": {
        "media": [
            {
                "file": "images/Clicker28x28.png",
                "menuIcon": true,
                "name": "Clicker",
                "type": "bitmap"
            }
        ]
    },
    "sdkVersion": "3",
    "shortName": "UmpClicker",
    "targetPlatforms": [
        "aplite",
        "basalt",
        "chalk"
    ],
    "uuid": "3cfc1e20-8569-417f-9c76-f0f03aa7d926",
    "versionLabel": "1.2",
    "watchapp": {
        "watchface": false
    }
}
